<?xml version="1.0" encoding="UTF-8"?>
<dao xmlns="http://jelix.org/ns/dao/1.0">
    <datasources>
        <primarytable name="poll" realname="poll" primarykey="id_poll" />
        <!--foreigntable name="poll_answer" realname="poll_answer" primarykey="id_answer" onforeignkey="id_poll"/-->
    </datasources>
    <record>
        <property name="id_poll" fieldname="id_poll" datatype="int" required="true"/>
        <property name="question" fieldname="question" datatype="string" required="true" maxlength="255"/>
        <property name="date_created" fieldname="date_created" datatype="int" required="true"/>
        <property name="status" fieldname="status" datatype="int" required="true"/>
        
        <!--property name="id_answer" table="poll_answer" fieldname="id_answer" datatype="int" required="true"/>
        <property name="answer" table="poll_answer" fieldname="answer" datatype="string" required="true" maxlength="255"/>
        -->
    </record>
    <factory>
        <!--<method name="findByStage" type="select/selectfirst/delete/update/php">
            <parameter name="" />
            <values>
                <value property="" value="" />
            </values>
            <conditions logic="and/or">
                <eq property="" value="" />
            </conditions>
            <order>
                <orderitem property="" way="asc/desc" />
            </order>
            <limit offset="" count=""/>
            <body><![CDATA[
            ]]></body>
        </method>-->
    </factory>
</dao>
