<?xml version="1.0" encoding="UTF-8"?>
<dao xmlns="http://jelix.org/ns/dao/1.0">
    <datasources>
        <primarytable name="read_forum" realname="read_forum" primarykey="id_user,id_forum" />
    </datasources>
    <record>
        <property name="id_user" fieldname="id_user" datatype="int" required="true"/>
        <property name="id_forum" fieldname="id_forum" datatype="int" required="true"/>
        <property name="date_read" fieldname="date_read" datatype="int" required="true"/>
    </record>
    <factory>
        <method name="deleteAll" type="delete">

        </method>
        <method name="deleteByUserId" type="delete">
          <parameter name="id_user" />
          <conditions>
            <eq property="id_user" expr="$id_user" />
          </conditions>
        </method>
        <method name="getUnreadForum" type="selectfirst">
          <parameter name="id_user" />
          <parameter name="id_forum" />
          <parameter name="date_read" />
          <conditions>
            <eq property="id_user" expr="$id_user" />
            <eq property="id_forum" expr="$id_forum" />
            <gt property="date_read" expr="$date_read" />
          </conditions>
        </method>
    </factory>
</dao>
